pygame_widgets/__init__.py
pygame_widgets/button.py
pygame_widgets/combobox.py
pygame_widgets/dropdown.py
pygame_widgets/exceptions.py
pygame_widgets/mouse.py
pygame_widgets/popup.py
pygame_widgets/progressbar.py
pygame_widgets/selection.py
pygame_widgets/slider.py
pygame_widgets/textbox.py
pygame_widgets/toggle.py
pygame_widgets/util.py
pygame_widgets/widget.py
pygame_widgets/animations/__init__.py
pygame_widgets/animations/animation.py
pygame_widgets-1.2.6.dist-info/LICENSE
pygame_widgets-1.2.6.dist-info/METADATA
pygame_widgets-1.2.6.dist-info/WHEEL
pygame_widgets-1.2.6.dist-info/top_level.txt
pygame_widgets-1.2.6.dist-info/RECORD
