Metadata-Version: 2.1
Name: pygame-widgets
Version: 1.2.6
Summary: Widgets for use with Pygame
Home-page: https://github.com/AustL/PygameWidgets
Author: AustL
Author-email: 21chydra@gmail.com
License: MIT
Classifier: Programming Language :: Python :: 3
Classifier: License :: OSI Approved :: MIT License
Classifier: Operating System :: OS Independent
Requires-Python: >=3.10
License-File: LICENSE
Requires-Dist: pyperclip>=1.8.0
